qubitron/__init__.py
qubitron/_compat.py
qubitron/_compat_test.py
qubitron/_doc.py
qubitron/_import.py
qubitron/_import_test.py
qubitron/_version.py
qubitron/_version_test.py
qubitron/conftest.py
qubitron/json_resolver_cache.py
qubitron/py.typed
qubitron/circuits/__init__.py
qubitron/circuits/_block_diagram_drawer.py
qubitron/circuits/_block_diagram_drawer_test.py
qubitron/circuits/_box_drawing_character_data.py
qubitron/circuits/_box_drawing_character_data_test.py
qubitron/circuits/_bucket_priority_queue.py
qubitron/circuits/_bucket_priority_queue_test.py
qubitron/circuits/circuit.py
qubitron/circuits/circuit_operation.py
qubitron/circuits/circuit_operation_test.py
qubitron/circuits/circuit_test.py
qubitron/circuits/frozen_circuit.py
qubitron/circuits/frozen_circuit_test.py
qubitron/circuits/insert_strategy.py
qubitron/circuits/insert_strategy_test.py
qubitron/circuits/moment.py
qubitron/circuits/moment_test.py
qubitron/circuits/optimization_pass.py
qubitron/circuits/optimization_pass_test.py
qubitron/circuits/qasm_output.py
qubitron/circuits/qasm_output_test.py
qubitron/circuits/text_diagram_drawer.py
qubitron/circuits/text_diagram_drawer_test.py
qubitron/contrib/__init__.py
qubitron/contrib/json.py
qubitron/contrib/json_test.py
qubitron/contrib/acquaintance/__init__.py
qubitron/contrib/acquaintance/bipartite.py
qubitron/contrib/acquaintance/bipartite_test.py
qubitron/contrib/acquaintance/devices.py
qubitron/contrib/acquaintance/devices_test.py
qubitron/contrib/acquaintance/executor.py
qubitron/contrib/acquaintance/executor_test.py
qubitron/contrib/acquaintance/gates.py
qubitron/contrib/acquaintance/gates_test.py
qubitron/contrib/acquaintance/inspection_utils.py
qubitron/contrib/acquaintance/inspection_utils_test.py
qubitron/contrib/acquaintance/mutation_utils.py
qubitron/contrib/acquaintance/mutation_utils_test.py
qubitron/contrib/acquaintance/optimizers.py
qubitron/contrib/acquaintance/optimizers_test.py
qubitron/contrib/acquaintance/permutation.py
qubitron-1.6.0.dev0.dist-info/licenses/AUTHORS
qubitron-1.6.0.dev0.dist-info/licenses/LICENSE
qubitron-1.6.0.dev0.dist-info/METADATA
qubitron-1.6.0.dev0.dist-info/WHEEL
qubitron-1.6.0.dev0.dist-info/top_level.txt
qubitron-1.6.0.dev0.dist-info/RECORD
