Metadata-Version: 2.4
Name: qubitron
Version: 1.6.0.dev0
Summary: A framework for creating, editing, and invoking Noisy Intermediate Scale Quantum (NISQ) circuits.
Home-page: http://github.com/amyssnippet/qubitron
Author: The Qubitron Developers
Author-email: qubitron-dev@googlegroups.com
Maintainer: Amol S
Maintainer-email: your-email@example.com
License: Apache-2.0
Keywords: quantum computing,qubitron,nisq,quantum circuit simulator,quantum programming,simulation
Classifier: Development Status :: 5 - Production/Stable
Classifier: Intended Audience :: Developers
Classifier: Intended Audience :: Education
Classifier: Intended Audience :: Science/Research
Classifier: License :: OSI Approved :: Apache Software License
Classifier: Operating System :: MacOS :: MacOS X
Classifier: Operating System :: Microsoft :: Windows
Classifier: Operating System :: POSIX :: Linux
Classifier: Programming Language :: Python :: 3
Classifier: Programming Language :: Python :: 3.11
Classifier: Programming Language :: Python :: 3.12
Classifier: Topic :: Scientific/Engineering :: Quantum Computing
Classifier: Topic :: Software Development :: Libraries :: Python Modules
Classifier: Typing :: Typed
Requires-Python: >=3.11.0
License-File: LICENSE
License-File: AUTHORS
Requires-Dist: numpy>=1.22
Requires-Dist: scipy
Requires-Dist: sympy
Requires-Dist: networkx
Dynamic: author
Dynamic: author-email
Dynamic: classifier
Dynamic: description
Dynamic: description-content-type
Dynamic: home-page
Dynamic: keywords
Dynamic: license
Dynamic: license-file
Dynamic: maintainer
Dynamic: maintainer-email
Dynamic: requires-dist
Dynamic: requires-python
Dynamic: summary
